pgexplode.py
pgexplode-0.2.0.dist-info/METADATA
pgexplode-0.2.0.dist-info/WHEEL
pgexplode-0.2.0.dist-info/entry_points.txt
pgexplode-0.2.0.dist-info/top_level.txt
pgexplode-0.2.0.dist-info/RECORD
