Metadata-Version: 2.1
Name: pgexplode
Version: 0.2.0
Summary: Utility for exploding a PostgreSQL table (and any related data) into separate schemas.
Home-page: https://github.com/dcwatson/pgexplode
Author: Dan Watson
Author-email: dcwatson@gmail.com
License: MIT
Project-URL: Documentation, https://dcwatson.github.io/pgexplode/
Platform: UNKNOWN
Classifier: Development Status :: 3 - Alpha
Classifier: Intended Audience :: Developers
Classifier: License :: OSI Approved :: MIT License
Classifier: Programming Language :: Python
Classifier: Programming Language :: Python :: 3
Requires-Dist: asyncpg
